pysell/__init__.py
pysell/__main__.py
pysell-1.3.5.dist-info/METADATA
pysell-1.3.5.dist-info/WHEEL
pysell-1.3.5.dist-info/entry_points.txt
pysell-1.3.5.dist-info/licenses/LICENSE
pysell-1.3.5.dist-info/RECORD
