Metadata-Version: 2.3
Name: pysell
Version: 1.3.5
Summary: A Python-based Simple E-Learning Language for the Rapid Creation of Interactive and Mobile-Friendly STEM Courses
Project-URL: Homepage, https://pysell.org
Project-URL: Repository, https://github.com/andreas-schwenk/pysell
Author-email: Andreas Schwenk <contact@compiler-construction.com>
Maintainer-email: Andreas Schwenk <contact@compiler-construction.com>
License:                     GNU GENERAL PUBLIC LICENSE
Keywords: assessement,dsl,learning,quiz,stem,teaching
Classifier: License :: OSI Approved :: GNU General Public License v3 (GPLv3)
Classifier: Operating System :: OS Independent
Classifier: Programming Language :: Python :: 3
Requires-Python: >=3.8
